resmico-1.2.2.dist-info/RECORD
resmico-1.2.2.dist-info/top_level.txt
resmico-1.2.2.dist-info/LICENSE
resmico-1.2.2.dist-info/WHEEL
resmico-1.2.2.dist-info/entry_points.txt
resmico-1.2.2.dist-info/METADATA
resmico.libs/libgomp-38ea1071.so.1.0.0
resmico.libs/libgomp-c869cbf0.so.1.0.0
resmico/utils.py
resmico/reader.cpython-38-x86_64-linux-gnu.so
resmico/contig_reader.hpp
resmico/filter_contigs.py
resmico/contig_reader.py
resmico/setup.py
resmico/__init__.py
resmico/bam2feat.py
resmico/train_binary_data.py
resmico/evaluate.py
resmico/models_fl.py
resmico/add_stats.py
resmico/__main__.py
resmico/bam2feat
resmico/reader.pyx
resmico/contig_reader.cpp
resmico/model/resmico.h5
resmico/model/stats_cov.json
resmico/tests/test_bam2feat.py
resmico/tests/test_contig_reader.py
resmico/tests/test_models_fl.py
resmico/tests/__init__.py
resmico/tests/test_train.py
resmico/tests/test_evaluate.py
resmico/tests/test_filter.py
resmico/tests/data/format_data.py
resmico/tests/data/__init__.py
resmico/commands/filter_contigs.py
resmico/commands/arguments.py
resmico/commands/__init__.py
resmico/commands/bam2feat.py
resmico/commands/train.py
resmico/commands/evaluate.py
